iCloudToGCal/__init__.py
iCloudToGCal/__main__.py
iCloudToGCal/__version__.py
iCloudToGCal/chromedriver/__init__.py
iCloudToGCal/chromedriver/installDriver.py
iCloudToGCal/GUI/__init__.py
iCloudToGCal/GUI/create.py
iCloudToGCal/GUI/GUI.py
iCloudToGCal/processdata/__init__.py
iCloudToGCal/processdata/data.py
iCloudToGCal/processdata/processAttendence.py
iCloudToGCal/processdata/processTable.py
iCloudToGCal/selenuimFunctions/__init__.py
iCloudToGCal/selenuimFunctions/Gform.py
iCloudToGCal/selenuimFunctions/iCloud.py
icloudtogcal-1.0.4.dist-info/entry_points.txt
icloudtogcal-1.0.4.dist-info/METADATA
icloudtogcal-1.0.4.dist-info/WHEEL
icloudtogcal-1.0.4.dist-info/RECORD
