Metadata-Version: 2.1
Name: icloudtogcal
Version: 1.0.4
Summary: Sync iCloud events to Google Calendar
Home-page: https://github.com/fjueic/iCloud-to-Google-Calender.git
Author: Rohit
Author-email: rohitmalik987789@gmail.com
Requires-Python: >=3.7,<4.0
Classifier: Programming Language :: Python :: 3
Classifier: Programming Language :: Python :: 3.7
Classifier: Programming Language :: Python :: 3.8
Classifier: Programming Language :: Python :: 3.9
Classifier: Programming Language :: Python :: 3.10
Classifier: Programming Language :: Python :: 3.11
Requires-Dist: beautifulsoup4 (>=4.9.3,<5.0.0)
Requires-Dist: bs4 (>=0.0.1,<0.0.2)
Requires-Dist: customtkinter (>=5.1.2,<6.0.0)
Requires-Dist: requests (>=2.28.2,<3.0.0)
Requires-Dist: selenium (>=3.141.0,<4.0.0)
Requires-Dist: setuptools (>=57.5.0,<58.0.0)
Project-URL: Repository, https://github.com/fjueic/iCloud-to-Google-Calender.git
